pollination/point_in_time_grid/__init__.py
pollination/point_in_time_grid/_postprocess_results.py
pollination/point_in_time_grid/_prepare_folder.py
pollination/point_in_time_grid/entry.py
pollination_point_in_time_grid-0.4.0.dist-info/LICENSE
pollination_point_in_time_grid-0.4.0.dist-info/METADATA
pollination_point_in_time_grid-0.4.0.dist-info/WHEEL
pollination_point_in_time_grid-0.4.0.dist-info/top_level.txt
pollination_point_in_time_grid-0.4.0.dist-info/RECORD
