Metadata-Version: 2.1
Name: pollination-point-in-time-grid
Version: 0.4.0
Summary: Point-in-time grid-based recipe for Pollination.
Home-page: https://github.com/pollination/point-in-time-grid
Author: ladybug-tools
Author-email: info@ladybug.tools
Maintainer: chris, ladybug-tools
Maintainer-email: chris@ladybug.tools, info@ladybug.tools
License: PolyForm Shield License 1.0.0, https://polyformproject.org/wp-content/uploads/2020/06/PolyForm-Shield-1.0.0.txt
Project-URL: icon, https://raw.githubusercontent.com/ladybug-tools/artwork/master/icons_components/honeybee/png/gridrecipe.png
Project-URL: docker, https://hub.docker.com/r/ladybugtools/honeybee-radiance
Keywords: honeybee,radiance,ladybug-tools,illuminance,irradiance,point-in-time-grid
License-File: LICENSE
Requires-Dist: pollination-honeybee-radiance>=0.22.73
Requires-Dist: pollination-alias>=0.11.15
Requires-Dist: pollination-path>=0.3.4
Provides-Extra: viz
Requires-Dist: pollination-honeybee-display>=0.1.13; extra == "viz"
